WES_Calculation/__init__.py
WES_Calculation/greenampt.py
WES_Calculation/gumbel.py
WES_Calculation/templateproj.py
WES_Calculation/wavespectra.py
WES_Calculation/windspeed.py
WES_Calculation/windwave.py
WES_Calculation/preprocess/__init__.py
WES_Calculation/preprocess/pre_greenampt.py
WES_Calculation/preprocess/pre_gumbel.py
WES_Calculation/preprocess/pre_wavespectra.py
WES_Calculation/preprocess/pre_windspeed.py
WES_Calculation/preprocess/pre_windwave.py
WES_Calculation/ref_func/__init__.py
WES_Calculation/ref_func/common_func.py
WES_Calculation/ref_func/windspeed_func.py
WES_Calculation/ref_func/windwave_func.py
WES_Calculation-7.4.6.dist-info/LICENSE
WES_Calculation-7.4.6.dist-info/METADATA
WES_Calculation-7.4.6.dist-info/WHEEL
WES_Calculation-7.4.6.dist-info/top_level.txt
WES_Calculation-7.4.6.dist-info/RECORD
