Metadata-Version: 2.1
Name: WES_Calculation
Version: 7.4.6
Summary: Mini Package for Waterfront Engineering Studio(WES) Calculation model, Currently include Greenampt, Gumbel Model Calculation
Home-page: https://github.com/bdfd/5.2-PyPi-WES_Calculation
Author: BDFD
Author-email: bdfd2005@gmail.com
Project-URL: Bug Tracker, https://github.com/bdfd/5.2-PyPi-WES_Calculation/issues
Classifier: Programming Language :: Python :: 3.6
Classifier: License :: OSI Approved :: MIT License
Classifier: Operating System :: OS Independent
Requires-Python: >=3.6
License-File: LICENSE
